cline_tools/__init__.py
orffinder/__init__.py
orffinder/orffinder.py
orffinder-1.8.data/scripts/orffinder-to-gff3
orffinder-1.8.data/scripts/orffinder-to-gtf
orffinder-1.8.data/scripts/orffinder-to-sequence
orffinder-1.8.dist-info/LICENSE
orffinder-1.8.dist-info/METADATA
orffinder-1.8.dist-info/WHEEL
orffinder-1.8.dist-info/top_level.txt
orffinder-1.8.dist-info/RECORD
