Metadata-Version: 2.1
Name: orffinder
Version: 1.8
Summary: Open Reading Frame finder natively coded in Python.
Home-page: https://github.com/Chokyotager/ORFFinder
Author: ChocoParrot
Author-email: lachocoparrot@gmail.com
License: UNKNOWN
Project-URL: Bug Tracker, https://github.com/Chokyotager/ORFFinder/issues
Platform: UNKNOWN
Classifier: Programming Language :: Python :: 3
Classifier: License :: OSI Approved :: MIT License
Classifier: Operating System :: OS Independent
Requires-Python: >=3.6
License-File: LICENSE
Requires-Dist: biopython (>=1.79)
